{"version":1,"resource":"file:///home/alice/repos/mc-combiner/.vscode/launch.json","entries":[{"id":"PIgt.json","timestamp":1731503365650},{"id":"GzwG.json","timestamp":1731503391107},{"id":"IWb9.json","timestamp":1731503467558},{"id":"rKvq.json","timestamp":1731503496089},{"id":"ve0t.json","timestamp":1731503522281},{"id":"jU1m.json","timestamp":1731503553786},{"id":"9m7K.json","timestamp":1731503575938},{"id":"S6mC.json","timestamp":1731503587481},{"id":"3E0J.json","timestamp":1731569199600},{"id":"wrq2.json","timestamp":1731569211693}]}