{"version":1,"resource":"file:///home/alice/.config/hypr/hypridle.conf","entries":[{"id":"bChh.conf","source":"textFileCreate.source","timestamp":1729148918459},{"id":"l4D2.conf","timestamp":1729149006866},{"id":"dUab.conf","timestamp":1729149017502},{"id":"9pcK.conf","timestamp":1729149871060},{"id":"mA1m.conf","timestamp":1729149893900},{"id":"IiwX.conf","timestamp":1729149967987},{"id":"Vnqb.conf","timestamp":1732952520741},{"id":"3tFo.conf","timestamp":1732952616375},{"id":"xIQC.conf","timestamp":1732952776757},{"id":"HKeq.conf","timestamp":1732952859247},{"id":"9vW0.conf","timestamp":1732952951940},{"id":"u9W3.conf","timestamp":1732953002480}]}